Metadata-Version: 2.1
Name: openbb-nightly
Version: 4.3.1.dev202408231811
Summary: Investment research for everyone, anywhere.
License: AGPL-3.0-only
Author: OpenBB Team
Author-email: hello@openbb.co
Requires-Python: >=3.9,<3.13
Classifier: License :: OSI Approved :: GNU Affero General Public License v3
Classifier: Programming Language :: Python :: 3
Classifier: Programming Language :: Python :: 3.9
Classifier: Programming Language :: Python :: 3.10
Classifier: Programming Language :: Python :: 3.11
Classifier: Programming Language :: Python :: 3.12
Requires-Dist: aiohttp (>=3.10.2,<4.0.0)
Requires-Dist: aiohttp-client-cache (>=0.11.0,<0.12.0)
Requires-Dist: aiosqlite (>=0.20.0,<0.21.0)
Requires-Dist: arch (>=7,<8)
Requires-Dist: bandit (>=1.7.5,<2.0.0)
Requires-Dist: black (>=24.4.2,<25.0.0)
Requires-Dist: bs4 (>=0.0.2,<0.0.3)
Requires-Dist: codespell (>=2.2.5,<3.0.0)
Requires-Dist: defusedxml (>=0.8.0rc2,<0.9.0)
Requires-Dist: exchange-calendars (>=4.5.4,<5.0.0)
Requires-Dist: fastapi (>=0.111.0,<0.112.0)
Requires-Dist: finvizfinance (>=1.0.0,<2.0.0)
Requires-Dist: html5lib (>=1.1,<2.0)
Requires-Dist: importlib-metadata (>=6.8.0,<7.0.0)
Requires-Dist: ipykernel (>=6.29.4,<7.0.0)
Requires-Dist: linearmodels (>=6,<7)
Requires-Dist: lxml (>=5.2.1,<6.0.0)
Requires-Dist: mypy (>=1.6.1,<2.0.0)
Requires-Dist: nasdaq-data-link (>=1.0.4,<2.0.0)
Requires-Dist: nbformat (>=5.9.2,<6.0.0)
Requires-Dist: numpy (>=1,<2)
Requires-Dist: pandas (>=1.5.3)
Requires-Dist: pandas-ta (>=0.3.14b,<0.4.0)
Requires-Dist: plotly (>=5.17.0,<6.0.0)
Requires-Dist: poetry (>=1.7.0,<2.0.0)
Requires-Dist: posthog (>=3.3.1,<4.0.0)
Requires-Dist: pre-commit (>=3.5.0,<4.0.0)
Requires-Dist: pydantic (>=2.5.1,<3.0.0)
Requires-Dist: pydocstyle (>=6.3.0,<7.0.0)
Requires-Dist: pyjwt (>=2.8.0,<3.0.0)
Requires-Dist: pylint (>=3.0.2,<4.0.0)
Requires-Dist: pytest (>=7.4.3,<8.0.0)
Requires-Dist: pytest-asyncio (>=0.23.2,<0.24.0)
Requires-Dist: pytest-cov (>=4.1.0,<5.0.0)
Requires-Dist: pytest-freezegun (>=0.4.2,<0.5.0)
Requires-Dist: pytest-recorder (>=0.3.0,<0.4.0)
Requires-Dist: pytest-subtests (>=0.11.0,<0.12.0)
Requires-Dist: python-dotenv (>=1.0.0,<2.0.0)
Requires-Dist: python-multipart (>=0.0.7,<0.0.8)
Requires-Dist: pywry (>=0.6.1,<0.7.0)
Requires-Dist: random-user-agent (>=1.0.1,<2.0.0)
Requires-Dist: requests (>=2.32.1,<3.0.0)
Requires-Dist: requests-cache (>=1.1.0,<2.0.0)
Requires-Dist: ruff (>=0.4.4,<0.5.0)
Requires-Dist: scikit-learn (>=1.5.0,<2.0.0)
Requires-Dist: scipy (>=1.10.0,<2.0.0)
Requires-Dist: statsmodels (>=0.14.0,<0.15.0)
Requires-Dist: tox (>=4.11.3,<5.0.0)
Requires-Dist: types-python-dateutil (>=2.8.19.14,<3.0.0.0)
Requires-Dist: types-toml (>=0.10.8.7,<0.11.0.0)
Requires-Dist: urllib3 (>1.26.16)
Requires-Dist: uuid7 (>=0.1.0,<0.2.0)
Requires-Dist: uvicorn (>=0.24,<0.25)
Requires-Dist: websockets (>=12.0,<13.0)
Requires-Dist: xmltodict (>=0.13.0,<0.14.0)
Requires-Dist: yfinance (>=0.2.40,<0.3.0)
